bring_api/__init__.py
bring_api/bring.py
bring_api/const.py
bring_api/exceptions.py
bring_api/helpers.py
bring_api/py.typed
bring_api/types.py
bring_api/locales/articles.de-AT.json
bring_api/locales/articles.de-CH.json
bring_api/locales/articles.de-DE.json
bring_api/locales/articles.en-AU.json
bring_api/locales/articles.en-CA.json
bring_api/locales/articles.en-GB.json
bring_api/locales/articles.en-US.json
bring_api/locales/articles.es-ES.json
bring_api/locales/articles.fr-CH.json
bring_api/locales/articles.fr-FR.json
bring_api/locales/articles.hu-HU.json
bring_api/locales/articles.it-CH.json
bring_api/locales/articles.it-IT.json
bring_api/locales/articles.nb-NO.json
bring_api/locales/articles.nl-NL.json
bring_api/locales/articles.pl-PL.json
bring_api/locales/articles.pt-BR.json
bring_api/locales/articles.ru-RU.json
bring_api/locales/articles.sv-SE.json
bring_api/locales/articles.tr-TR.json
bring_api-1.1.1.dist-info/licenses/LICENSE
bring_api-1.1.1.dist-info/METADATA
bring_api-1.1.1.dist-info/WHEEL
bring_api-1.1.1.dist-info/top_level.txt
bring_api-1.1.1.dist-info/RECORD
