Metadata-Version: 2.4
Name: bring-api
Version: 1.1.1
Summary: Unofficial package to access Bring! shopping lists API.
Author-email: Cyrill Raccaud <cyrill.raccaud+pypi@gmail.com>, Manfred Dennerlein Rodelo <manfred@dennerlein.name>
License-Expression: MIT
Project-URL: Documentation, https://miaucl.github.io/bring-api/
Project-URL: Source, https://github.com/miaucl/bring-api
Project-URL: Issues, https://github.com/miaucl/bring-api/issues
Project-URL: Release notes, https://github.com/miaucl/bring-api/releases
Classifier: Programming Language :: Python :: 3
Classifier: Operating System :: OS Independent
Requires-Python: >=3.11
License-File: LICENSE
Requires-Dist: aiohttp>=3.10
Requires-Dist: mashumaro>=3.13
Requires-Dist: orjson>=3.10
Dynamic: license-file
